shopify_converter/__init__.py
shopify_converter/converter.py
shopify_converter/order_converter.py
shopify_converter/product_converter.py
shopify_converter-1.2.2.dist-info/LICENSE
shopify_converter-1.2.2.dist-info/METADATA
shopify_converter-1.2.2.dist-info/WHEEL
shopify_converter-1.2.2.dist-info/top_level.txt
shopify_converter-1.2.2.dist-info/RECORD
